matriarch/.DS_Store
matriarch/__init__.py
matriarch-0.0.1.dist-info/WHEEL
matriarch-0.0.1.dist-info/METADATA
matriarch-0.0.1.dist-info/RECORD
